Moore Detector/moore_detector.v
module moore_detector
(
    input  wire rst,
    input  wire clk,
    input  wire din,
    output dout
);
localparam S0 = 3'd0,S1 = 3'd1,S2 = 3'd2,S3 = 3'd3,S4 = 3'd4;
reg [2:0]current_state,next_state;
always @(posedge clk or negedge rst)
begin
    if(!rst)
    begin
        current_state <= 3'd0;
    end
    else
    begin
        current_state <= next_state;
    end
end

always@(*)
begin
    case(current_state)
    S0:next_state <= din ? S1: S0;
    S1:next_state <= din ? S1: S2;
    S2:next_state <= din ? S3: S0;
    S3:next_state <= din ? S4: S2;
    S4:next_state <= din ? S1: S2;
    default:next_state <= S0;
    endcase
end

assign dout = (current_state == S4);
endmodule

Moore Detector/tb_moore_detector.v
`include "moore_detector.v"
module tb_mooredetector;
reg  clk;
reg  rst;
reg  din;
wire dout;

moore_detector DUT
(
    .clk(clk),
    .rst(rst),
    .din(din),
    .dout(dout)
);

initial clk = 1'b0;
always #5 clk = ~clk;

initial begin
rst = 1'b0;
din = 1'b0;
#10
$monitor("|Time = %0t|din = %0b|dout =%0b|",$time,din,dout);
rst = 1'b1;
din = 1'b1;#10;
din = 1'b0;#10;
din = 1'b1;#10;
din = 1'b1;#10;
din = 1'b1;#10;
din = 1'b0;#10;
din = 1'b1;#10;


#100;
$finish;
end
initial
begin
    $dumpfile("dump3.vcd");
    $dumpvars(0,tb_mooredetector);
end
endmodule

Moore Detector/dump3.vcd
$date
	Mon Feb 16 08:58:08 2026
$end
$version
	Icarus Verilog
$end
$timescale
	1s
$end
$scope module tb_mooredetector $end
$var wire 1 ! dout $end
$var reg 1 " clk $end
$var reg 1 # din $end
$var reg 1 $ rst $end
$scope module DUT $end
$var wire 1 " clk $end
$var wire 1 # din $end
$var wire 1 $ rst $end
$var wire 1 ! dout $end
$var parameter 3 % S0 $end
$var parameter 3 & S1 $end
$var parameter 3 ' S2 $end
$var parameter 3 ( S3 $end
$var parameter 3 ) S4 $end
$var reg 3 * current_state [2:0] $end
$var reg 3 + next_state [2:0] $end
$upscope $end
$upscope $end
$enddefinitions $end
$comment Show the parameter values. $end
$dumpall
b100 )
b11 (
b10 '
b1 &
b0 %
$end
#0
$dumpvars
b0 +
b0 *
0$
0#
0"
0!
$end
#5
1"
#10
b1 +
0"
1#
1$
#15
b1 *
1"
#20
b10 +
0"
0#
#25
b0 +
b10 *
1"
#30
b11 +
0"
1#
#35
b100 +
b11 *
1"
#40
0"
#45
b1 +
1!
b100 *
1"
#50
0"
#55
0!
b1 *
1"
#60
b10 +
0"
0#
#65
b0 +
b10 *
1"
#70
b11 +
0"
1#
#75
b100 +
b11 *
1"
#80
0"
#85
b1 +
1!
b100 *
1"
#90
0"
#95
0!
b1 *
1"
